cli.py
week_service.py
core/__init__.py
core/database.py
core/match_loader.py
core/standings_calculator.py
core/week_divider.py
utils/__init__.py
utils/logger.py
week_service-1.0.2.dist-info/METADATA
week_service-1.0.2.dist-info/WHEEL
week_service-1.0.2.dist-info/entry_points.txt
week_service-1.0.2.dist-info/top_level.txt
week_service-1.0.2.dist-info/RECORD
